exercise_client/__init__.py
exercise_client/config.py
exercise_client/cutie.py
exercise_client/cutie_example.py
exercise_client/docker.py
exercise_client/gitlab.py
exercise_client/jupyter.py
exercise_client/select.py
exercise_client/utils.py
exercise_client-0.7.0.dist-info/LICENSE
exercise_client-0.7.0.dist-info/METADATA
exercise_client-0.7.0.dist-info/WHEEL
exercise_client-0.7.0.dist-info/entry_points.txt
exercise_client-0.7.0.dist-info/top_level.txt
exercise_client-0.7.0.dist-info/RECORD
