Metadata-Version: 2.1
Name: exercise-client
Version: 0.7.0
Summary: Tool for launching jupyter from docker containers
Author: Kasper Munch
Author-email: kaspermunch@birc.au.dk
Classifier: Programming Language :: Python :: 3
Classifier: License :: OSI Approved :: MIT License
Classifier: Operating System :: OS Independent
Requires-Python: >=3.8
License-File: LICENSE
Requires-Dist: requests >=2.32
Requires-Dist: colorama >=0.4
Requires-Dist: readchar >=4.0
Requires-Dist: click
